mcp_rs_publish_stdio/__init__.py
mcp_rs_publish_stdio/command.py
mcp_rs_publish_stdio-0.1.8.dist-info/METADATA
mcp_rs_publish_stdio-0.1.8.dist-info/WHEEL
mcp_rs_publish_stdio-0.1.8.dist-info/entry_points.txt
mcp_rs_publish_stdio-0.1.8.dist-info/top_level.txt
mcp_rs_publish_stdio-0.1.8.dist-info/RECORD
