Metadata-Version: 2.4
Name: mcp_rs_publish_stdio
Version: 0.1.8
Summary: mcp_rs_publish_stdio
Requires-Python: >=3.13
Requires-Dist: mcp[cli]>=1.13.1
